ada_verona/__init__.py
ada_verona/analysis/report_creator.py
ada_verona/database/__init__.py
ada_verona/database/epsilon_status.py
ada_verona/database/epsilon_value_result.py
ada_verona/database/experiment_repository.py
ada_verona/database/verification_context.py
ada_verona/database/verification_result.py
ada_verona/database/vnnlib_property.py
ada_verona/database/dataset/data_point.py
ada_verona/database/dataset/experiment_dataset.py
ada_verona/database/dataset/image_file_dataset.py
ada_verona/database/dataset/pytorch_experiment_dataset.py
ada_verona/database/machine_learning_model/__init__.py
ada_verona/database/machine_learning_model/network.py
ada_verona/database/machine_learning_model/onnx_network.py
ada_verona/database/machine_learning_model/pytorch_network.py
ada_verona/database/machine_learning_model/torch_model_wrapper.py
ada_verona/dataset_sampler/dataset_sampler.py
ada_verona/dataset_sampler/predictions_based_sampler.py
ada_verona/epsilon_value_estimator/__init__.py
ada_verona/epsilon_value_estimator/binary_search_epsilon_value_estimator.py
ada_verona/epsilon_value_estimator/epsilon_value_estimator.py
ada_verona/epsilon_value_estimator/iterative_epsilon_value_estimator.py
ada_verona/util/logger.py
ada_verona/verification_module/__init__.py
ada_verona/verification_module/attack_estimation_module.py
ada_verona/verification_module/auto_verify_module.py
ada_verona/verification_module/test_verification_module.py
ada_verona/verification_module/verification_module.py
ada_verona/verification_module/attacks/attack.py
ada_verona/verification_module/attacks/auto_attack_wrapper.py
ada_verona/verification_module/attacks/fgsm_attack.py
ada_verona/verification_module/attacks/pgd_attack.py
ada_verona/verification_module/property_generator/one2any_property_generator.py
ada_verona/verification_module/property_generator/one2one_property_generator.py
ada_verona/verification_module/property_generator/property_generator.py
ada_verona-1.0.0.dist-info/METADATA
ada_verona-1.0.0.dist-info/WHEEL
ada_verona-1.0.0.dist-info/licenses/LICENSE
ada_verona-1.0.0.dist-info/RECORD
