Metadata-Version: 2.4
Name: ada-verona
Version: 1.0.0
Summary: Neural Network Robustness Analysis Framework
Project-URL: Homepage, https://github.com/ADA-research/VERONA
Project-URL: Repository, https://github.com/ADA-research/VERONA
Project-URL: Documentation, https://ada-research.github.io/VERONA/
Project-URL: Issues, https://github.com/ADA-research/VERONA/issues
Author-email: Annelot Bosman <a.w.bosman@liacs.leidenuniv.nl>, Aaron Berger <A.Berger@tudelft.nl>, Hendrik Baacke <hendrik.baacke@rwth-aachen.de>, Jan van Rijn <jan.vanrijn@liacs.leidenuniv.nl>, "Holger H. Hoos" <hh@aim.rwth-aachen.de>
License:                                  Apache License
License-File: LICENSE
Keywords: AI safety,adversarial,adversarial attacks,adversarial robustness,neural networks,robustness,verification
Classifier: Development Status :: 3 - Alpha
Classifier: Intended Audience :: Science/Research
Classifier: License :: OSI Approved :: Apache Software License
Classifier: Operating System :: POSIX :: Linux
Classifier: Programming Language :: Python :: 3.10
Classifier: Programming Language :: Python :: 3.11
Classifier: Topic :: Scientific/Engineering :: Artificial Intelligence
Requires-Python: <3.11,>=3.10
Requires-Dist: matplotlib>=3.10.0
Requires-Dist: numpy>=1.24.3
Requires-Dist: onnx2torch>=1.5.14
Requires-Dist: onnx>=1.14.0
Requires-Dist: onnxruntime>=1.14.1
Requires-Dist: pandas>=2.0.1
Requires-Dist: pyyaml>=6.0.1
Requires-Dist: result>=0.9.0
Requires-Dist: seaborn>=0.13.2
Requires-Dist: torch>=2.6.0
Requires-Dist: torchvision>=0.18.1
Requires-Dist: typing-extensions
Provides-Extra: gpu
Requires-Dist: nvidia-cublas-cu12<13.0.0,>=12.1.0; extra == 'gpu'
Requires-Dist: nvidia-cuda-cupti-cu12<13.0.0,>=12.1.0; extra == 'gpu'
Requires-Dist: nvidia-cuda-nvrtc-cu12<13.0.0,>=12.1.0; extra == 'gpu'
Requires-Dist: nvidia-cuda-runtime-cu12<13.0.0,>=12.1.0; extra == 'gpu'
Requires-Dist: nvidia-cudnn-cu12<10.0.0,>=9.1.0; extra == 'gpu'
Requires-Dist: nvidia-cufft-cu12<12.0.0,>=11.0.0; extra == 'gpu'
Requires-Dist: nvidia-curand-cu12<11.0.0,>=10.3.0; extra == 'gpu'
Requires-Dist: nvidia-cusolver-cu12<12.0.0,>=11.4.0; extra == 'gpu'
Requires-Dist: nvidia-cusparse-cu12<13.0.0,>=12.1.0; extra == 'gpu'
Requires-Dist: nvidia-nccl-cu12<3.0.0,>=2.20.0; extra == 'gpu'
Requires-Dist: nvidia-nvjitlink-cu12<13.0.0,>=12.4.0; extra == 'gpu'
Requires-Dist: nvidia-nvtx-cu12<13.0.0,>=12.1.0; extra == 'gpu'
Requires-Dist: triton<4.0.0,>=3.2.0; extra == 'gpu'
